<XML encoding="UTF-8" standalone="yes" version="1.0">
<foros>

  <anime>
    <titulo>Dr Stone</titulo>
    <cap>1</cap>
    <iurl>animesAmontonxD/videos/3081103031928045</iurl>
  </anime>

  <anime>
    <titulo>Dr Stone</titulo>
    <cap>2</cap>
    <iurl>animesAmontonxD/videos/654491538657016</iurl>
  </anime>

  <anime>
    <titulo>Dr Stone</titulo>
    <cap>3</cap>
    <iurl>animesAmontonxD/videos/137047304348315</iurl>
  </anime>

  <anime>
    <titulo>Dr Stone</titulo>
    <cap>4</cap>
    <iurl>ElReyOtaku/videos/226634758545290</iurl>
  </anime>

  <anime>
    <titulo>Dr Stone</titulo>
    <cap>5</cap>
    <iurl>ElReyOtaku/videos/2300546550238480</iurl>
  </anime>

  <anime>
    <titulo>Dr Stone</titulo>
    <cap>6</cap>
    <iurl>ElReyOtaku/videos/2569879749900683</iurl>
  </anime>

  <anime>
    <titulo>Dr Stone</titulo>
    <cap>7</cap>
    <iurl>ElReyOtaku/videos/256639308699756</iurl>
  </anime>

  <anime>
    <titulo>Dr Stone</titulo>
    <cap>8</cap>
    <iurl>ElReyOtaku/videos/511243299765438</iurl>
  </anime>

  <anime>
    <titulo>Dr Stone</titulo>
    <cap>9</cap>
    <iurl>314319982778430/videos/373819566625467</iurl>
  </anime>

  <anime>
    <titulo>Dr Stone</titulo>
    <cap>10</cap>
    <iurl>ElReyOtaku/videos/210937473566815</iurl>
  </anime>

  <anime>
    <titulo>Dr Stone</titulo>
    <cap>11</cap>
    <iurl>100006173538876/videos/2555737577975335</iurl>
  </anime>

  <anime>
    <titulo>Dr Stone</titulo>
    <cap>12</cap>
    <iurl>100006173538876/videos/2555750927974000</iurl>
  </anime>

  <anime>
    <titulo>Dr Stone</titulo>
    <cap>13</cap>
    <iurl>100006173538876/videos/2557975954418164</iurl>
  </anime>

  <anime>
    <titulo>Dr Stone</titulo>
    <cap>14</cap>
    <iurl>100006173538876/videos/2555786217970471</iurl>
  </anime>

  <anime>
    <titulo>Dr Stone</titulo>
    <cap>15</cap>
    <iurl>100006173538876/videos/2558202301062196</iurl>
  </anime>

  <anime>
    <titulo>Dr Stone</titulo>
    <cap>16</cap>
    <iurl>100006173538876/videos/2559197474296012</iurl>
  </anime>

  <anime>
    <titulo>Dr Stone</titulo>
    <cap>17</cap>
    <iurl>100006173538876/videos/2559198924295867</iurl>
  </anime>

  <anime>
    <titulo>Dr Stone</titulo>
    <cap>18</cap>
    <iurl>100006173538876/videos/2559199174295842</iurl>
  </anime>

  <anime>
    <titulo>Dr Stone</titulo>
    <cap>19</cap>
    <iurl>100006173538876/videos/2559199357629157</iurl>
  </anime>

  <anime>
    <titulo>Dr Stone</titulo>
    <cap>20</cap>
    <iurl>100006173538876/videos/2559199780962448</iurl>
  </anime>

  <anime>
    <titulo>Dr Stone</titulo>
    <cap>21</cap>
    <iurl>100006173538876/videos/2562631893952570</iurl>
  </anime>

  <anime>
    <titulo>Dr Stone</titulo>
    <cap>22</cap>
    <iurl>100006173538876/videos/2562632863952473</iurl>
  </anime>

  <anime>
    <titulo>Dr Stone</titulo>
    <cap>23</cap>
    <iurl>100006173538876/videos/2562633777285715</iurl>
  </anime>

  <anime>
    <titulo>Dr Stone</titulo>
    <cap>24</cap>
    <iurl>100006173538876/videos/2562639747285118</iurl>
  </anime>

</foros>
</XML>
